simplestoragering/CSLattice.c
simplestoragering/CSLattice.cp310-win_amd64.pyd
simplestoragering/CSLattice.pyi
simplestoragering/Drift.c
simplestoragering/Drift.cp310-win_amd64.pyd
simplestoragering/Drift.pyi
simplestoragering/DrivingTerms.py
simplestoragering/DynamicAperture.py
simplestoragering/HBend.c
simplestoragering/HBend.cp310-win_amd64.pyd
simplestoragering/HBend.pyi
simplestoragering/Octupole.c
simplestoragering/Octupole.cp310-win_amd64.pyd
simplestoragering/Octupole.pyi
simplestoragering/Quadrupole.c
simplestoragering/Quadrupole.cp310-win_amd64.pyd
simplestoragering/Quadrupole.pyi
simplestoragering/Sextupole.c
simplestoragering/Sextupole.cp310-win_amd64.pyd
simplestoragering/Sextupole.pyi
simplestoragering/__init__.py
simplestoragering/c_functions.c
simplestoragering/c_functions.cp310-win_amd64.pyd
simplestoragering/components.c
simplestoragering/components.cp310-win_amd64.pyd
simplestoragering/components.pyi
simplestoragering/exceptions.py
simplestoragering/functions.py
simplestoragering/globalvars.c
simplestoragering/globalvars.cp310-win_amd64.pyd
simplestoragering/globalvars.pyi
simplestoragering/line_matrix.c
simplestoragering/line_matrix.cp310-win_amd64.pyd
simplestoragering/objectives.py
simplestoragering/plotlib.py
simplestoragering/track.c
simplestoragering/track.cp310-win_amd64.pyd
simplestoragering/track.pyi
simplestoragering/atintegrators/BndMPoleSymplectic4Pass.c
simplestoragering/atintegrators/BndStrMPoleSymplectic4Pass.c
simplestoragering-0.0.2.dist-info/LICENSE
simplestoragering-0.0.2.dist-info/METADATA
simplestoragering-0.0.2.dist-info/WHEEL
simplestoragering-0.0.2.dist-info/top_level.txt
simplestoragering-0.0.2.dist-info/RECORD
