Metadata-Version: 2.1
Name: simplestoragering
Version: 0.0.2
Summary: simple storage ring for single particle dynamics simulation.
Author-email: Bingfeng WEI <wbf2016@mail.ustc.edu.cn>
License: MIT License
Project-URL: Homepage, https://github.com/wei0852/simplestoragering
Project-URL: Repository, https://github.com/wei0852/simplestoragering.git
Project-URL: Issues, https://github.com/wei0852/simplestoragering/issues
Classifier: Development Status :: 4 - Beta
Classifier: Operating System :: OS Independent
Classifier: License :: OSI Approved :: MIT License
Classifier: Programming Language :: Cython
Classifier: Programming Language :: Python :: 3
Requires-Python: >=3.8
License-File: LICENSE
Requires-Dist: numpy <2,>=1.18
Requires-Dist: matplotlib >3.4.0
Requires-Dist: PyNAFF
